cpppackage7-1.0.0.dist-info/METADATA
cpppackage7-1.0.0.dist-info/pydist.json
cpppackage7-1.0.0.dist-info/RECORD
cpppackage7-1.0.0.dist-info/top_level.txt
cpppackage7-1.0.0.dist-info/WHEEL
django_pdf_generator/pdf_generator.py
django_pdf_generator/__init__.py
